Metadata-Version: 1.1
Name: argparse-oappend
Version: 0.0.1
Summary: An append action for argparse that overrides the default.
Home-page: http://github.org/wrwrwr/argparse-oappend
Author: Wojtek Ruszczewski
Author-email: python@wr.waw.pl
License: MIT
Platform: UNKNOWN
Classifier: Development Status :: 4 - Beta
Classifier: Intended Audience :: Developers
Classifier: Topic :: Software Development
Classifier: License :: OSI Approved :: MIT License
Classifier: Programming Language :: Python :: 3.4
Classifier: Programming Language :: Python :: 3.5
